filezen/__init__.py
filezen/constants.py
filezen/types.py
filezen/utils.py
filezen/zen_api.py
filezen/zen_error.py
filezen/zen_storage.py
filezen/zen_upload.py
filezen_python-0.1.4.dist-info/METADATA
filezen_python-0.1.4.dist-info/WHEEL
filezen_python-0.1.4.dist-info/licenses/LICENSE
filezen_python-0.1.4.dist-info/RECORD
